oterm/__init__.py
oterm/config.py
oterm/log.py
oterm/ollamaclient.py
oterm/types.py
oterm/utils.py
oterm/app/__init__.py
oterm/app/chat_edit.py
oterm/app/chat_export.py
oterm/app/chat_rename.py
oterm/app/css.py
oterm/app/image_browser.py
oterm/app/log_viewer.py
oterm/app/mcp_prompt.py
oterm/app/oterm.py
oterm/app/oterm.tcss
oterm/app/prompt_history.py
oterm/app/pull_model.py
oterm/app/splash.py
oterm/app/themes/__init__.py
oterm/app/themes/solarized_dark.py
oterm/app/widgets/__init__.py
oterm/app/widgets/caps.py
oterm/app/widgets/chat.py
oterm/app/widgets/image.py
oterm/app/widgets/prompt.py
oterm/app/widgets/tool_select.py
oterm/cli/__init__.py
oterm/cli/oterm.py
oterm/store/__init__.py
oterm/store/store.py
oterm/store/upgrades/__init__.py
oterm/store/upgrades/v0_12_0.py
oterm/store/upgrades/v0_13_1.py
oterm/store/upgrades/v0_1_11.py
oterm/store/upgrades/v0_1_6.py
oterm/store/upgrades/v0_2_0.py
oterm/store/upgrades/v0_2_4.py
oterm/store/upgrades/v0_2_8.py
oterm/store/upgrades/v0_3_0.py
oterm/store/upgrades/v0_4_0.py
oterm/store/upgrades/v0_5_1.py
oterm/store/upgrades/v0_6_0.py
oterm/store/upgrades/v0_7_0.py
oterm/store/upgrades/v0_9_0.py
oterm/tools/__init__.py
oterm/tools/date_time.py
oterm/tools/external.py
oterm/tools/shell.py
oterm/tools/think.py
oterm/tools/mcp/__init__.py
oterm/tools/mcp/client.py
oterm/tools/mcp/logging.py
oterm/tools/mcp/prompts.py
oterm/tools/mcp/sampling.py
oterm/tools/mcp/setup.py
oterm/tools/mcp/tools.py
oterm-0.14.7.dist-info/METADATA
oterm-0.14.7.dist-info/WHEEL
oterm-0.14.7.dist-info/entry_points.txt
oterm-0.14.7.dist-info/licenses/LICENSE
oterm-0.14.7.dist-info/RECORD
