Metadata-Version: 2.4
Name: oterm
Version: 0.14.7
Summary: The terminal client for Ollama.
Project-URL: Homepage, https://github.com/ggozad/oterm
Project-URL: Repository, https://github.com/ggozad/oterm
Project-URL: Issues, https://github.com/ggozad/oterm/issues
Project-URL: Documentation, https://ggozad.github.io/oterm/
Author-email: Yiorgis Gozadinos <ggozadinos@gmail.com>
License: MIT
License-File: LICENSE
Classifier: Development Status :: 4 - Beta
Classifier: Environment :: Console
Classifier: Intended Audience :: Developers
Classifier: Operating System :: MacOS
Classifier: Operating System :: Microsoft :: Windows :: Windows 10
Classifier: Operating System :: Microsoft :: Windows :: Windows 11
Classifier: Operating System :: POSIX :: Linux
Classifier: Programming Language :: Python :: 3.10
Classifier: Programming Language :: Python :: 3.11
Classifier: Programming Language :: Python :: 3.12
Classifier: Typing :: Typed
Requires-Python: >=3.10
Requires-Dist: aiosql<15,>=14.1
Requires-Dist: aiosqlite<0.23,>=0.22.0
Requires-Dist: fastmcp<2.15,>=2.14.1
Requires-Dist: ollama<0.7,>=0.6.1
Requires-Dist: packaging<26,>=25.0
Requires-Dist: pillow<13,>=12.0.0
Requires-Dist: pydantic<2.13,>=2.12.5
Requires-Dist: python-dotenv>=1.0.1
Requires-Dist: textual-image<0.9.0,>=0.8.4
Requires-Dist: textual-speedups>=0.2.0
Requires-Dist: textual<6.12,>=6.11.0
Requires-Dist: textualeffects>=0.2.0
Requires-Dist: typer<0.21,>=0.20.1
